issue/__init__.py
issue/actions.py
issue/apps.py
issue/builder.py
issue/check.py
issue/models.py
issue/urls.py
issue/version.py
issue/management/__init__.py
issue/management/commands/__init__.py
issue/management/commands/check_assertions.py
issue/management/commands/respond_to_issues.py
issue/migrations/0001_0004_squashed.py
issue/migrations/0005_responder_allow_retry.py
issue/migrations/__init__.py
issue/migrations/datamigrations/__init__.py
issue/tests/__init__.py
issue/tests/action_tests.py
issue/tests/builder_tests.py
issue/tests/checker_tests.py
issue/tests/management_command_tests.py
issue/tests/model_tests.py
issue/tests/models.py
django_issue-3.5.1.dist-info/LICENSE
django_issue-3.5.1.dist-info/METADATA
django_issue-3.5.1.dist-info/WHEEL
django_issue-3.5.1.dist-info/top_level.txt
django_issue-3.5.1.dist-info/RECORD
